eventsource/__init__.py
eventsource/config.py
eventsource/exceptions.py
eventsource/protocols.py
eventsource/py.typed
eventsource/types.py
eventsource/aggregates/__init__.py
eventsource/aggregates/base.py
eventsource/aggregates/repository.py
eventsource/aggregates/snapshot_manager.py
eventsource/aggregates/task_manager.py
eventsource/bus/__init__.py
eventsource/bus/interface.py
eventsource/bus/kafka.py
eventsource/bus/memory.py
eventsource/bus/rabbitmq.py
eventsource/bus/redis.py
eventsource/events/__init__.py
eventsource/events/base.py
eventsource/events/registry.py
eventsource/handlers/__init__.py
eventsource/handlers/adapter.py
eventsource/handlers/decorators.py
eventsource/handlers/registry.py
eventsource/locks/__init__.py
eventsource/locks/postgresql.py
eventsource/migration/README.md
eventsource/migration/__init__.py
eventsource/migration/bulk_copier.py
eventsource/migration/consistency.py
eventsource/migration/coordinator.py
eventsource/migration/cutover.py
eventsource/migration/dual_write.py
eventsource/migration/exceptions.py
eventsource/migration/metrics.py
eventsource/migration/models.py
eventsource/migration/position_mapper.py
eventsource/migration/router.py
eventsource/migration/status_streamer.py
eventsource/migration/subscription_migrator.py
eventsource/migration/sync_lag_tracker.py
eventsource/migration/write_pause.py
eventsource/migration/repositories/__init__.py
eventsource/migration/repositories/audit_log.py
eventsource/migration/repositories/migration.py
eventsource/migration/repositories/position_mapping.py
eventsource/migration/repositories/routing.py
eventsource/migrations/SCHEMA_DESIGN.md
eventsource/migrations/__init__.py
eventsource/migrations/schemas/all.sql
eventsource/migrations/schemas/checkpoints.sql
eventsource/migrations/schemas/dlq.sql
eventsource/migrations/schemas/events.sql
eventsource/migrations/schemas/events_partitioned.sql
eventsource/migrations/schemas/outbox.sql
eventsource/migrations/schemas/snapshots.sql
eventsource_py-0.5.0.dist-info/METADATA
eventsource_py-0.5.0.dist-info/WHEEL
eventsource_py-0.5.0.dist-info/licenses/LICENSE
eventsource_py-0.5.0.dist-info/RECORD
