Metadata-Version: 2.4
Name: eventsource-py
Version: 0.5.0
Summary: Production-ready event sourcing library for Python
Project-URL: Homepage, https://github.com/tyevans/eventsource-py
Project-URL: Documentation, https://tyevans.github.io/eventsource-py
Project-URL: Repository, https://github.com/tyevans/eventsource-py
Project-URL: Changelog, https://github.com/tyevans/eventsource-py/blob/main/CHANGELOG.md
Author-email: Ty Evans <tyevans@gmail.com>
License: MIT
License-File: LICENSE
Keywords: cqrs,ddd,domain-driven-design,event-sourcing,events
Classifier: Development Status :: 4 - Beta
Classifier: Intended Audience :: Developers
Classifier: License :: OSI Approved :: MIT License
Classifier: Programming Language :: Python :: 3
Classifier: Programming Language :: Python :: 3.11
Classifier: Programming Language :: Python :: 3.12
Classifier: Programming Language :: Python :: 3.13
Classifier: Topic :: Software Development :: Libraries :: Python Modules
Classifier: Typing :: Typed
Requires-Python: >=3.11
Requires-Dist: pydantic<3.0,>=2.0
Requires-Dist: redis>=5.0
Requires-Dist: sqlalchemy<3.0,>=2.0
Provides-Extra: all
Requires-Dist: aio-pika>=9.0.0; extra == 'all'
Requires-Dist: aiokafka<1.0.0,>=0.9.0; extra == 'all'
Requires-Dist: aiosqlite<1.0,>=0.19.0; extra == 'all'
Requires-Dist: asyncpg<1.0,>=0.27.0; extra == 'all'
Requires-Dist: opentelemetry-api<2.0,>=1.0; extra == 'all'
Requires-Dist: opentelemetry-sdk<2.0,>=1.0; extra == 'all'
Requires-Dist: redis<6.0,>=5.0; extra == 'all'
Provides-Extra: all-backends
Requires-Dist: aiosqlite<1.0,>=0.19.0; extra == 'all-backends'
Requires-Dist: asyncpg<1.0,>=0.27.0; extra == 'all-backends'
Provides-Extra: benchmark
Requires-Dist: pytest-benchmark>=4.0.0; extra == 'benchmark'
Provides-Extra: dev
Requires-Dist: mypy>=1.8; extra == 'dev'
Requires-Dist: pre-commit>=4.0; extra == 'dev'
Requires-Dist: pytest-asyncio>=0.23; extra == 'dev'
Requires-Dist: pytest-benchmark>=4.0.0; extra == 'dev'
Requires-Dist: pytest-cov>=4.0; extra == 'dev'
Requires-Dist: pytest>=8.0; extra == 'dev'
Requires-Dist: ruff>=0.14.8; extra == 'dev'
Requires-Dist: testcontainers>=4.0; extra == 'dev'
Provides-Extra: docs
Requires-Dist: mkdocs-material>=9.5; extra == 'docs'
Requires-Dist: mkdocs>=1.5; extra == 'docs'
Requires-Dist: mkdocstrings[python]>=0.24; extra == 'docs'
Requires-Dist: pymdown-extensions>=10.0; extra == 'docs'
Provides-Extra: kafka
Requires-Dist: aiokafka<1.0.0,>=0.9.0; extra == 'kafka'
Provides-Extra: kafka-schema-registry
Requires-Dist: aiokafka<1.0.0,>=0.9.0; extra == 'kafka-schema-registry'
Requires-Dist: confluent-kafka<3.0.0,>=2.0.0; extra == 'kafka-schema-registry'
Provides-Extra: postgresql
Requires-Dist: asyncpg<1.0,>=0.27.0; extra == 'postgresql'
Provides-Extra: rabbitmq
Requires-Dist: aio-pika>=9.0.0; extra == 'rabbitmq'
Provides-Extra: redis
Requires-Dist: redis<6.0,>=5.0; extra == 'redis'
Provides-Extra: sqlite
Requires-Dist: aiosqlite<1.0,>=0.19.0; extra == 'sqlite'
Provides-Extra: telemetry
Requires-Dist: opentelemetry-api<2.0,>=1.0; extra == 'telemetry'
Requires-Dist: opentelemetry-sdk<2.0,>=1.0; extra == 'telemetry'
